ai_24sea/__init__.py
ai_24sea/version.py
ai_24sea/modeler/__init__.py
ai_24sea/modeler/config.py
ai_24sea/modeler/constants.py
ai_24sea/modeler/misc/__init__.py
ai_24sea/modeler/misc/preprocessors.py
ai_24sea/modeler/misc/utils.py
ai_24sea/modeler/tasks/__init__.py
ai_24sea/modeler/tasks/ingest.py
ai_24sea/modeler/tasks/optimize.py
ai_24sea/modeler/tasks/split.py
ai_24sea/modeler/tasks/train.py
ai_24sea/modeler/tasks/transform.py
ai_24sea-1.0.0.dist-info/licenses/LICENSE
ai_24sea-1.0.0.dist-info/WHEEL
ai_24sea-1.0.0.dist-info/METADATA
ai_24sea-1.0.0.dist-info/RECORD
