Metadata-Version: 2.4
Name: ai-24sea
Version: 1.0.0
Summary: A package containing general functionality for 24sea ai/ml related topics
Author-email: Panagiotis Konis <panagiotis.konis@24sea.eu>
Maintainer-email: Panagiotis Konis <panagiotis.konis@24sea.eu>
Requires-Python: >=3.9.0,<3.12
Classifier: Development Status :: 1 - Planning
Classifier: Environment :: Console
Classifier: Intended Audience :: Science/Research
Classifier: Intended Audience :: Information Technology
Classifier: License :: OSI Approved :: GNU General Public License v3 (GPLv3)
Classifier: Natural Language :: English
Classifier: Operating System :: POSIX :: Linux
Classifier: Programming Language :: Python :: 3
Classifier: Programming Language :: Python :: 3.9
Classifier: Programming Language :: Python :: 3.10
Classifier: Programming Language :: Python :: 3.11
License-File: LICENSE
Requires-Dist: api-24sea>=2.1.1,<3
Requires-Dist: prefect==3.3.6
Requires-Dist: pandas
Requires-Dist: numpy
Requires-Dist: mlflow==2.22.0
Requires-Dist: psycopg2-binary
Requires-Dist: azure-storage-blob>=12.23.1
Requires-Dist: tabulate
Requires-Dist: markdown
Requires-Dist: omegaconf>=2.3.0
Project-URL: Documentation, https://dev.azure.com/24sea/DataDevOps/_git/24sea_ai_modeler_cookiecutter
Project-URL: Homepage, https://www.24sea.eu/
Project-URL: Repository, https://dev.azure.com/24sea/DataDevOps/_git/24sea_ai_modeler_cookiecutter
